linkedin_package/__init__.py
linkedin_package/csv_scrape.py
linkedin_package/json_srape.py
package/__init__.py
package/csv_scrape.py
package/json_srape.py
linkedin_information_collections_scraper-0.0.22.dist-info/LICENSE
linkedin_information_collections_scraper-0.0.22.dist-info/METADATA
linkedin_information_collections_scraper-0.0.22.dist-info/WHEEL
linkedin_information_collections_scraper-0.0.22.dist-info/top_level.txt
linkedin_information_collections_scraper-0.0.22.dist-info/RECORD
